RFglovesPackages/RFgloves.py
RFglovesPackages/__init__.py
RFglovesPackages-0.1.dist-info/METADATA
RFglovesPackages-0.1.dist-info/WHEEL
RFglovesPackages-0.1.dist-info/top_level.txt
RFglovesPackages-0.1.dist-info/RECORD
