Metadata-Version: 2.1
Name: RFglovesPackages
Version: 0.1
Summary: Testing installation of Package
Home-page: UNKNOWN
Author: Zhu Yanjin
Author-email: 582820136@qq.com
License: MIT
Platform: UNKNOWN
